arman_k/__init__.py
arman_k/yo.py
arman_k-0.0.3.dist-info/LICENSE
arman_k-0.0.3.dist-info/METADATA
arman_k-0.0.3.dist-info/WHEEL
arman_k-0.0.3.dist-info/top_level.txt
arman_k-0.0.3.dist-info/RECORD
