Metadata-Version: 2.1
Name: arman-k
Version: 0.0.3
Summary: arman_k
Author: Arman Kumar
Author-email: armank3001@gmail.com
Keywords: binary,math,mathematics,k.v.ofdumdum,arman kumar
Classifier: Development Status :: 1 - Planning
Classifier: Intended Audience :: Developers
Classifier: Programming Language :: Python :: 3
Classifier: Operating System :: Unix
Classifier: Operating System :: MacOS :: MacOS X
Classifier: Operating System :: Microsoft :: Windows
License-File: LICENSE
